Metadata-Version: 2.1
Name: gw_remnant
Version: 0.2.0
Summary: Python package to extract remnant black hole properties from gravitational waveforms
Home-page: https://github.com/tousifislam/gw_remnant
Author: Tousif Islam, Scott Field, Gaurav Khanna
Author-email: tousifislam24@gmail.com
Maintainer: Tousif Islam
Maintainer-email: tousifislam24@gmail.com
License: MIT
Project-URL: Bug Reports, https://github.com/tousifislam/gw_remnant/issues
Project-URL: Source, https://github.com/tousifislam/gw_remnant
Keywords: gravitational waves,black holes,numerical relativity,remnant properties
Classifier: Development Status :: 4 - Beta
Classifier: Intended Audience :: Science/Research
Classifier: Intended Audience :: Other Audience
Classifier: Topic :: Scientific/Engineering
Classifier: Topic :: Scientific/Engineering :: Astronomy
Classifier: Topic :: Scientific/Engineering :: Mathematics
Classifier: Topic :: Scientific/Engineering :: Physics
Classifier: License :: OSI Approved :: MIT License
Classifier: Natural Language :: English
Classifier: Programming Language :: Python
Classifier: Programming Language :: Python :: 3
Classifier: Programming Language :: Python :: 3.8
Classifier: Programming Language :: Python :: 3.9
Classifier: Programming Language :: Python :: 3.10
Classifier: Programming Language :: Python :: 3.11
Classifier: Programming Language :: Python :: 3.12
Classifier: Programming Language :: Python :: 3.13
Classifier: Operating System :: OS Independent
Requires-Python: >=3.8
License-File: LICENSE
Requires-Dist: numpy>=1.20.0
Requires-Dist: scipy>=1.7.0
Requires-Dist: matplotlib>=3.3.0
Requires-Dist: gwtools
Provides-Extra: surrogates
Requires-Dist: gwsurrogate; extra == "surrogates"
Requires-Dist: surfinBH; extra == "surrogates"
Provides-Extra: lal
Requires-Dist: lal; extra == "lal"
Requires-Dist: lalsimulation; extra == "lal"
Provides-Extra: all
Requires-Dist: gwsurrogate; extra == "all"
Requires-Dist: surfinBH; extra == "all"
Requires-Dist: lal; extra == "all"
Requires-Dist: lalsimulation; extra == "all"
Provides-Extra: dev
Requires-Dist: pytest>=6.0; extra == "dev"
Requires-Dist: pytest-cov; extra == "dev"
Requires-Dist: black; extra == "dev"
Requires-Dist: flake8; extra == "dev"
Requires-Dist: ipython; extra == "dev"
Requires-Dist: jupyter; extra == "dev"
